app/configs/functions_config.py
app/configs/main_config.py
app/data/default_products_substrs.txt
app/data/default_store_positions.json
app/functions/common.py
app/functions/methods_functions.py
app/main.py
app/models/orders_data_types.py
app/routers/orders.py
python_practice_field-0.0.3.dist-info/METADATA
python_practice_field-0.0.3.dist-info/WHEEL
python_practice_field-0.0.3.dist-info/RECORD
