Metadata-Version: 2.1
Name: python-practice-field
Version: 0.0.3
Summary: 
Author: alexnazarv
Author-email: alexnazarv@gmail.com
Requires-Python: >=3.10,<3.11
Classifier: Programming Language :: Python :: 3
Classifier: Programming Language :: Python :: 3.10
Requires-Dist: fastapi (>=0.101.0,<0.102.0)
Requires-Dist: uvicorn[standard] (==0.23.2)
